<?xml version="1.0" encoding="UTF-8"?>
<!-- Generated by Fujitsu XWand 7.1.0042 -->
<link:linkbase xmlns:link="http://www.xbrl.org/2003/linkbase" xmlns:xbrli="http://www.xbrl.org/2003/instance" xmlns:xlink="http://www.w3.org/1999/xlink" xmlns:xsi="http://www.w3.org/2001/XMLSchema-instance" xsi:schemaLocation="http://www.xbrl.org/2003/linkbase http://www.xbrl.org/2003/xbrl-linkbase-2003-12-31.xsd" xmlns:p-mc="http://www.c-ebs.org/eu/fr/esrs/corep/2005-12-31/p-mc-2005-12-31">
  <link:labelLink xlink:type="extended" xlink:role="http://www.xbrl.org/2003/role/link">
    <link:loc xlink:type="locator" xlink:href="p-mc-2005-12-31.xsd#p-mc_MKRSACOMDomain" xlink:label="label_MarketRiskStandardisedApproachesForCommodities_1134399079534_0" xlink:title="label_MarketRiskStandardisedApproachesForCommodities"/>
    <link:label xlink:type="resource" xlink:label="label_MarketRiskStandardisedApproachesForCommodities_1134399079534_1" xlink:role="http://www.xbrl.org/2003/role/label" xlink:title="label_MarketRiskStandardisedApproachesForCommodities" xml:lang="en" id="label_MarketRiskStandardisedApproachesForCommodities_1134399079534_1">MKR SA COM (Domain)</link:label>
    <link:labelArc xlink:type="arc" xlink:arcrole="http://www.xbrl.org/2003/arcrole/concept-label" xlink:from="label_MarketRiskStandardisedApproachesForCommodities_1134399079534_0" xlink:to="label_MarketRiskStandardisedApproachesForCommodities_1134399079534_1" xlink:title="label: MarketRiskStandardisedApproachesForCommodities to label_MarketRiskStandardisedApproachesForCommodities"/>
    <link:loc xlink:type="locator" xlink:href="p-mc-2005-12-31.xsd#p-mc_AllPositions" xlink:label="label_AllPositions_1134399120582_0" xlink:title="label_AllPositions"/>
    <link:label xlink:type="resource" xlink:label="label_AllPositions_1134399120582_1" xlink:role="http://www.xbrl.org/2003/role/label" xlink:title="label_AllPositions" xml:lang="en" id="label_AllPositions_1134399120582_1">All Positions</link:label>
    <link:labelArc xlink:type="arc" xlink:arcrole="http://www.xbrl.org/2003/arcrole/concept-label" xlink:from="label_AllPositions_1134399120582_0" xlink:to="label_AllPositions_1134399120582_1" xlink:title="label: AllPositions to label_AllPositions"/>
    <link:label xlink:type="resource" xlink:label="label_AllPositions" xlink:role="http://www.xbrl.org/2003/role/documentation" xlink:title="label_AllPositions" xml:lang="en" id="label_AllPositions">Core layer</link:label>
    <link:labelArc xlink:type="arc" xlink:arcrole="http://www.xbrl.org/2003/arcrole/concept-label" xlink:from="label_AllPositions_1134399120582_0" xlink:to="label_AllPositions" xlink:title="label: AllPositions to label_AllPositions"/>
    <link:loc xlink:type="locator" xlink:href="p-mc-2005-12-31.xsd#p-mc_AllPositionsLong" xlink:label="label_AllPositionsLong_1134399153379_0" xlink:title="label_AllPositionsLong"/>
    <link:label xlink:type="resource" xlink:label="label_AllPositionsLong_1134399153379_1" xlink:role="http://www.xbrl.org/2003/role/label" xlink:title="label_AllPositionsLong" xml:lang="en" id="label_AllPositionsLong_1134399153379_1">Long</link:label>
    <link:labelArc xlink:type="arc" xlink:arcrole="http://www.xbrl.org/2003/arcrole/concept-label" xlink:from="label_AllPositionsLong_1134399153379_0" xlink:to="label_AllPositionsLong_1134399153379_1" xlink:title="label: AllPositionsLong to label_AllPositionsLong"/>
    <link:label xlink:type="resource" xlink:label="label_AllPositionsLong" xlink:role="http://www.xbrl.org/2003/role/documentation" xlink:title="label_AllPositionsLong" xml:lang="en" id="label_AllPositionsLong">Core layer</link:label>
    <link:labelArc xlink:type="arc" xlink:arcrole="http://www.xbrl.org/2003/arcrole/concept-label" xlink:from="label_AllPositionsLong_1134399153379_0" xlink:to="label_AllPositionsLong" xlink:title="label: AllPositionsLong to label_AllPositionsLong"/>
    <link:loc xlink:type="locator" xlink:href="p-mc-2005-12-31.xsd#p-mc_AllPositionsShort" xlink:label="label_AllPositionsShort_1134399179596_0" xlink:title="label_AllPositionsShort"/>
    <link:label xlink:type="resource" xlink:label="label_AllPositionsShort_1134399179596_1" xlink:role="http://www.xbrl.org/2003/role/label" xlink:title="label_AllPositionsShort" xml:lang="en" id="label_AllPositionsShort_1134399179596_1">Short</link:label>
    <link:labelArc xlink:type="arc" xlink:arcrole="http://www.xbrl.org/2003/arcrole/concept-label" xlink:from="label_AllPositionsShort_1134399179596_0" xlink:to="label_AllPositionsShort_1134399179596_1" xlink:title="label: AllPositionsShort to label_AllPositionsShort"/>
    <link:label xlink:type="resource" xlink:label="label_AllPositionsShort" xlink:role="http://www.xbrl.org/2003/role/documentation" xlink:title="label_AllPositionsShort" xml:lang="en" id="label_AllPositionsShort">Core layer</link:label>
    <link:labelArc xlink:type="arc" xlink:arcrole="http://www.xbrl.org/2003/arcrole/concept-label" xlink:from="label_AllPositionsShort_1134399179596_0" xlink:to="label_AllPositionsShort" xlink:title="label: AllPositionsShort to label_AllPositionsShort"/>
    <link:loc xlink:type="locator" xlink:href="p-mc-2005-12-31.xsd#p-mc_MemorandumItemsPositionsPurelyStockFinancing" xlink:label="label_MemorandumItems_1134399213033_0" xlink:title="label_MemorandumItems"/>
    <link:label xlink:type="resource" xlink:label="label_MemorandumItems_1134399213033_1" xlink:role="http://www.xbrl.org/2003/role/label" xlink:title="label_MemorandumItems" xml:lang="en" id="label_MemorandumItems_1134399213033_1">Memorandum Items: Positions Which are Purely Stock Financing</link:label>
    <link:labelArc xlink:type="arc" xlink:arcrole="http://www.xbrl.org/2003/arcrole/concept-label" xlink:from="label_MemorandumItems_1134399213033_0" xlink:to="label_MemorandumItems_1134399213033_1" xlink:title="label: MemorandumItems to label_MemorandumItems"/>
    <link:label xlink:type="resource" xlink:label="label_MemorandumItems" xlink:role="http://www.xbrl.org/2003/role/documentation" xlink:title="label_MemorandumItems" xml:lang="en" id="label_MemorandumItems">Detailed layer</link:label>
    <link:labelArc xlink:type="arc" xlink:arcrole="http://www.xbrl.org/2003/arcrole/concept-label" xlink:from="label_MemorandumItems_1134399213033_0" xlink:to="label_MemorandumItems" xlink:title="label: MemorandumItems to label_MemorandumItems"/>
    <link:loc xlink:type="locator" xlink:href="p-mc-2005-12-31.xsd#p-mc_MemorandumItemsLong" xlink:label="label_MemorandumItemsLong_1134399288921_0" xlink:title="label_MemorandumItemsLong"/>
    <link:label xlink:type="resource" xlink:label="label_MemorandumItemsLong_1134399288921_1" xlink:role="http://www.xbrl.org/2003/role/label" xlink:title="label_MemorandumItemsLong" xml:lang="en" id="label_MemorandumItemsLong_1134399288921_1">Long</link:label>
    <link:labelArc xlink:type="arc" xlink:arcrole="http://www.xbrl.org/2003/arcrole/concept-label" xlink:from="label_MemorandumItemsLong_1134399288921_0" xlink:to="label_MemorandumItemsLong_1134399288921_1" xlink:title="label: MemorandumItemsLong to label_MemorandumItemsLong"/>
    <link:label xlink:type="resource" xlink:label="label_MemorandumItemsLong" xlink:role="http://www.xbrl.org/2003/role/documentation" xlink:title="label_MemorandumItemsLong" xml:lang="en" id="label_MemorandumItemsLong">Detailed layer</link:label>
    <link:labelArc xlink:type="arc" xlink:arcrole="http://www.xbrl.org/2003/arcrole/concept-label" xlink:from="label_MemorandumItemsLong_1134399288921_0" xlink:to="label_MemorandumItemsLong" xlink:title="label: MemorandumItemsLong to label_MemorandumItemsLong"/>
    <link:loc xlink:type="locator" xlink:href="p-mc-2005-12-31.xsd#p-mc_MemorandumItemsShort" xlink:label="label_MemorandumItemsShort_1134399309860_0" xlink:title="label_MemorandumItemsShort"/>
    <link:label xlink:type="resource" xlink:label="label_MemorandumItemsShort_1134399309860_1" xlink:role="http://www.xbrl.org/2003/role/label" xlink:title="label_MemorandumItemsShort" xml:lang="en" id="label_MemorandumItemsShort_1134399309860_1">Short</link:label>
    <link:labelArc xlink:type="arc" xlink:arcrole="http://www.xbrl.org/2003/arcrole/concept-label" xlink:from="label_MemorandumItemsShort_1134399309860_0" xlink:to="label_MemorandumItemsShort_1134399309860_1" xlink:title="label: MemorandumItemsShort to label_MemorandumItemsShort"/>
    <link:label xlink:type="resource" xlink:label="label_MemorandumItemsShort" xlink:role="http://www.xbrl.org/2003/role/documentation" xlink:title="label_MemorandumItemsShort" xml:lang="en" id="label_MemorandumItemsShort">Detailed layer</link:label>
    <link:labelArc xlink:type="arc" xlink:arcrole="http://www.xbrl.org/2003/arcrole/concept-label" xlink:from="label_MemorandumItemsShort_1134399309860_0" xlink:to="label_MemorandumItemsShort" xlink:title="label: MemorandumItemsShort to label_MemorandumItemsShort"/>
    <link:loc xlink:type="locator" xlink:href="p-mc-2005-12-31.xsd#p-mc_NetPositions" xlink:label="label_NetPositions_1134399353532_0" xlink:title="label_NetPositions"/>
    <link:label xlink:type="resource" xlink:label="label_NetPositions_1134399353532_1" xlink:role="http://www.xbrl.org/2003/role/label" xlink:title="label_NetPositions" xml:lang="en" id="label_NetPositions_1134399353532_1">Net Positions</link:label>
    <link:labelArc xlink:type="arc" xlink:arcrole="http://www.xbrl.org/2003/arcrole/concept-label" xlink:from="label_NetPositions_1134399353532_0" xlink:to="label_NetPositions_1134399353532_1" xlink:title="label: NetPositions to label_NetPositions"/>
    <link:label xlink:type="resource" xlink:label="label_NetPositions" xlink:role="http://www.xbrl.org/2003/role/documentation" xlink:title="label_NetPositions" xml:lang="en" id="label_NetPositions">Core layer</link:label>
    <link:labelArc xlink:type="arc" xlink:arcrole="http://www.xbrl.org/2003/arcrole/concept-label" xlink:from="label_NetPositions_1134399353532_0" xlink:to="label_NetPositions" xlink:title="label: NetPositions to label_NetPositions"/>
    <link:loc xlink:type="locator" xlink:href="p-mc-2005-12-31.xsd#p-mc_NetPositionsLong" xlink:label="label_NetPositionsLong_1134399380801_0" xlink:title="label_NetPositionsLong"/>
    <link:label xlink:type="resource" xlink:label="label_NetPositionsLong_1134399380801_1" xlink:role="http://www.xbrl.org/2003/role/label" xlink:title="label_NetPositionsLong" xml:lang="en" id="label_NetPositionsLong_1134399380801_1">Long</link:label>
    <link:labelArc xlink:type="arc" xlink:arcrole="http://www.xbrl.org/2003/arcrole/concept-label" xlink:from="label_NetPositionsLong_1134399380801_0" xlink:to="label_NetPositionsLong_1134399380801_1" xlink:title="label: NetPositionsLong to label_NetPositionsLong"/>
    <link:label xlink:type="resource" xlink:label="label_NetPositionsLong" xlink:role="http://www.xbrl.org/2003/role/documentation" xlink:title="label_NetPositionsLong" xml:lang="en" id="label_NetPositionsLong">Core layer</link:label>
    <link:labelArc xlink:type="arc" xlink:arcrole="http://www.xbrl.org/2003/arcrole/concept-label" xlink:from="label_NetPositionsLong_1134399380801_0" xlink:to="label_NetPositionsLong" xlink:title="label: NetPositionsLong to label_NetPositionsLong"/>
    <link:loc xlink:type="locator" xlink:href="p-mc-2005-12-31.xsd#p-mc_NetPositionsShort" xlink:label="label_NetPositionsShort_1134399398837_0" xlink:title="label_NetPositionsShort"/>
    <link:label xlink:type="resource" xlink:label="label_NetPositionsShort_1134399398837_1" xlink:role="http://www.xbrl.org/2003/role/label" xlink:title="label_NetPositionsShort" xml:lang="en" id="label_NetPositionsShort_1134399398837_1">Short</link:label>
    <link:labelArc xlink:type="arc" xlink:arcrole="http://www.xbrl.org/2003/arcrole/concept-label" xlink:from="label_NetPositionsShort_1134399398837_0" xlink:to="label_NetPositionsShort_1134399398837_1" xlink:title="label: NetPositionsShort to label_NetPositionsShort"/>
    <link:label xlink:type="resource" xlink:label="label_NetPositionsShort" xlink:role="http://www.xbrl.org/2003/role/documentation" xlink:title="label_NetPositionsShort" xml:lang="en" id="label_NetPositionsShort">Core layer</link:label>
    <link:labelArc xlink:type="arc" xlink:arcrole="http://www.xbrl.org/2003/arcrole/concept-label" xlink:from="label_NetPositionsShort_1134399398837_0" xlink:to="label_NetPositionsShort" xlink:title="label: NetPositionsShort to label_NetPositionsShort"/>
    <link:loc xlink:type="locator" xlink:href="p-mc-2005-12-31.xsd#p-mc_PositionsSubjectToCapitalCharge" xlink:label="label_PositionsSubjectToCapitalCharge_1134399434327_0" xlink:title="label_PositionsSubjectToCapitalCharge"/>
    <link:label xlink:type="resource" xlink:label="label_PositionsSubjectToCapitalCharge_1134399434327_1" xlink:role="http://www.xbrl.org/2003/role/label" xlink:title="label_PositionsSubjectToCapitalCharge" xml:lang="en" id="label_PositionsSubjectToCapitalCharge_1134399434327_1">Positions Subject to Capital Charge</link:label>
    <link:labelArc xlink:type="arc" xlink:arcrole="http://www.xbrl.org/2003/arcrole/concept-label" xlink:from="label_PositionsSubjectToCapitalCharge_1134399434327_0" xlink:to="label_PositionsSubjectToCapitalCharge_1134399434327_1" xlink:title="label: PositionsSubjectToCapitalCharge to label_PositionsSubjectToCapitalCharge"/>
    <link:label xlink:type="resource" xlink:label="label_PositionsSubjectToCapitalCharge" xlink:role="http://www.xbrl.org/2003/role/documentation" xlink:title="label_PositionsSubjectToCapitalCharge" xml:lang="en" id="label_PositionsSubjectToCapitalCharge">Core layer</link:label>
    <link:labelArc xlink:type="arc" xlink:arcrole="http://www.xbrl.org/2003/arcrole/concept-label" xlink:from="label_PositionsSubjectToCapitalCharge_1134399434327_0" xlink:to="label_PositionsSubjectToCapitalCharge" xlink:title="label: PositionsSubjectToCapitalCharge to label_PositionsSubjectToCapitalCharge"/>
    <link:loc xlink:type="locator" xlink:href="p-mc-2005-12-31.xsd#p-mc_CapitalRequirements" xlink:label="label_CapitalRequirements_1134399877465_0" xlink:title="label_CapitalRequirements"/>
    <link:label xlink:type="resource" xlink:label="label_CapitalRequirements_1134399877465_1" xlink:role="http://www.xbrl.org/2003/role/label" xlink:title="label_CapitalRequirements" xml:lang="en" id="label_CapitalRequirements_1134399877465_1">Capital Requirements</link:label>
    <link:labelArc xlink:type="arc" xlink:arcrole="http://www.xbrl.org/2003/arcrole/concept-label" xlink:from="label_CapitalRequirements_1134399877465_0" xlink:to="label_CapitalRequirements_1134399877465_1" xlink:title="label: CapitalRequirements to label_CapitalRequirements"/>
    <link:label xlink:type="resource" xlink:label="label_CapitalRequirements" xlink:role="http://www.xbrl.org/2003/role/documentation" xlink:title="label_CapitalRequirements" xml:lang="en" id="label_CapitalRequirements">Core layer</link:label>
    <link:labelArc xlink:type="arc" xlink:arcrole="http://www.xbrl.org/2003/arcrole/concept-label" xlink:from="label_CapitalRequirements_1134399877465_0" xlink:to="label_CapitalRequirements" xlink:title="label: CapitalRequirements to label_CapitalRequirements"/>
  </link:labelLink>
</link:linkbase>
